presign/__init__.py
presign/__main__.py
presign-0.1.dist-info/LICENSE
presign-0.1.dist-info/METADATA
presign-0.1.dist-info/WHEEL
presign-0.1.dist-info/entry_points.txt
presign-0.1.dist-info/top_level.txt
presign-0.1.dist-info/RECORD
